virden_jobs/__init__.py
virden_jobs/__main__.py
virden_jobs/facebook_client.py
virden_jobs/main.py
virden_jobs/common/__init__.py
virden_jobs/common/job.py
virden_jobs/common/web_content.py
virden_jobs/common/yaml.py
vjobs-0.1.2.dist-info/LICENSE
vjobs-0.1.2.dist-info/METADATA
vjobs-0.1.2.dist-info/WHEEL
vjobs-0.1.2.dist-info/top_level.txt
vjobs-0.1.2.dist-info/RECORD
