Metadata-Version: 2.1
Name: vjobs
Version: 0.1.2
Summary: Posts jobs scraped from websites to facebook
Home-page: https://gitlab.com/flaxking/virden-jobs
Author: flaxking
Author-email: flaxking@digitalnostril.com
License: UNKNOWN
Platform: UNKNOWN
Classifier: Programming Language :: Python :: 3
Classifier: License :: OSI Approved :: MIT License
Classifier: Operating System :: OS Independent
Requires-Dist: pyyaml (==5.1.1)
Requires-Dist: beautifulsoup4 (==4.8.0)
Requires-Dist: facebook-sdk (==3.1.0)
